Metadata-Version: 2.1
Name: pypidemo2
Version: 0.0.2
Summary: A small example package
Home-page: https://github.com/vcancy/spider80s
Author: vcancy
Author-email: happiness1019@gmail.com
License: MIT
Keywords: demo
Platform: UNKNOWN
Classifier: License :: OSI Approved :: MIT License
Classifier: Programming Language :: Python
Classifier: Intended Audience :: Developers
Classifier: Operating System :: OS Independent
